apibase/__init__.py
apibase/base.py
apibase/exceptions.py
apibase/logging_helper.py
apibase/network.py
apibase/read_configs.py
apibase/utils.py
py_apibase-0.1.0.dist-info/METADATA
py_apibase-0.1.0.dist-info/WHEEL
py_apibase-0.1.0.dist-info/RECORD
