Metadata-Version: 2.1
Name: py-apibase
Version: 0.1.0
Summary: is a lightweight Python library that simplifies the creation of API clients
License: MIT
Author: Basri
Author-email: h@basri.me
Requires-Python: >=3.12,<4.0
Classifier: License :: OSI Approved :: MIT License
Classifier: Programming Language :: Python :: 3
Classifier: Programming Language :: Python :: 3.12
Requires-Dist: requests (>=2.32.3,<3.0.0)
